[
    {
        "username": "Person_3",
        "ip": 33,
        "what": "xd"
    },
    {
        "username": "Person_3",
        "ip": 33,
        "what": "xd"
    },
    {
        "username": "mama",
        "ip": "127.0.0.1",
        "searched": ""
    },
    {
        "username": "mama",
        "ip": "127.0.0.1",
        "searched": "hehe"
    },
    {
        "username": "mama",
        "ip": "127.0.0.1",
        "searched": ""
    },
    {
        "username": "mama",
        "ip": "127.0.0.1",
        "searched": "1"
    },
    {
        "username": "mama",
        "ip": "127.0.0.1",
        "searched": "2"
    }
]